{
  "schema_version": 2,
  "index_type": "directory-manifest",
  "summary": {
    "root": "/home/runner/work/plant/plant/재배로그/박/2024_박/20240626",
    "path": "재배로그/박/2024_박/20240626",
    "generated_at": "2026-07-09T17:50:19+00:00",
    "file_count": 32,
    "directory_count": 0,
    "direct_file_count": 32,
    "direct_directory_count": 0,
    "total_size": 228804403,
    "total_size_human": "218.2 MB"
  },
  "tree": {
    "type": "directory",
    "name": "20240626",
    "path": "재배로그/박/2024_박/20240626",
    "index": "재배로그/박/2024_박/20240626/files.json",
    "modified": "2026-07-09T17:49:55+00:00",
    "children": [
      {
        "type": "file",
        "name": "20240626_193115.jpg",
        "path": "재배로그/박/2024_박/20240626/20240626_193115.jpg",
        "extension": "jpg",
        "group": "image",
        "mime_type": "image/jpeg",
        "size": 2503773,
        "size_human": "2.4 MB",
        "modified": "2026-07-09T17:49:55+00:00",
        "security": {
          "private": false,
          "source": "public"
        }
      },
      {
        "type": "file",
        "name": "20240626_193117.jpg",
        "path": "재배로그/박/2024_박/20240626/20240626_193117.jpg",
        "extension": "jpg",
        "group": "image",
        "mime_type": "image/jpeg",
        "size": 3311368,
        "size_human": "3.2 MB",
        "modified": "2026-07-09T17:49:55+00:00",
        "security": {
          "private": false,
          "source": "public"
        }
      },
      {
        "type": "file",
        "name": "20240626_193124.mp4",
        "path": "재배로그/박/2024_박/20240626/20240626_193124.mp4",
        "extension": "mp4",
        "group": "video",
        "mime_type": "video/mp4",
        "size": 20518873,
        "size_human": "19.6 MB",
        "modified": "2026-07-09T17:49:55+00:00",
        "security": {
          "private": false,
          "source": "public"
        }
      },
      {
        "type": "file",
        "name": "20240626_193143.mp4",
        "path": "재배로그/박/2024_박/20240626/20240626_193143.mp4",
        "extension": "mp4",
        "group": "video",
        "mime_type": "video/mp4",
        "size": 37780691,
        "size_human": "36.0 MB",
        "modified": "2026-07-09T17:49:55+00:00",
        "security": {
          "private": false,
          "source": "public"
        }
      },
      {
        "type": "file",
        "name": "20240626_193210.mp4",
        "path": "재배로그/박/2024_박/20240626/20240626_193210.mp4",
        "extension": "mp4",
        "group": "video",
        "mime_type": "video/mp4",
        "size": 13796023,
        "size_human": "13.2 MB",
        "modified": "2026-07-09T17:49:55+00:00",
        "security": {
          "private": false,
          "source": "public"
        }
      },
      {
        "type": "file",
        "name": "20240626_193242.jpg",
        "path": "재배로그/박/2024_박/20240626/20240626_193242.jpg",
        "extension": "jpg",
        "group": "image",
        "mime_type": "image/jpeg",
        "size": 2613764,
        "size_human": "2.5 MB",
        "modified": "2026-07-09T17:49:55+00:00",
        "security": {
          "private": false,
          "source": "public"
        }
      },
      {
        "type": "file",
        "name": "20240626_193243.jpg",
        "path": "재배로그/박/2024_박/20240626/20240626_193243.jpg",
        "extension": "jpg",
        "group": "image",
        "mime_type": "image/jpeg",
        "size": 3824618,
        "size_human": "3.6 MB",
        "modified": "2026-07-09T17:49:55+00:00",
        "security": {
          "private": false,
          "source": "public"
        }
      },
      {
        "type": "file",
        "name": "20240626_193245.jpg",
        "path": "재배로그/박/2024_박/20240626/20240626_193245.jpg",
        "extension": "jpg",
        "group": "image",
        "mime_type": "image/jpeg",
        "size": 3778942,
        "size_human": "3.6 MB",
        "modified": "2026-07-09T17:49:55+00:00",
        "security": {
          "private": false,
          "source": "public"
        }
      },
      {
        "type": "file",
        "name": "20240626_193246.jpg",
        "path": "재배로그/박/2024_박/20240626/20240626_193246.jpg",
        "extension": "jpg",
        "group": "image",
        "mime_type": "image/jpeg",
        "size": 3004551,
        "size_human": "2.9 MB",
        "modified": "2026-07-09T17:49:55+00:00",
        "security": {
          "private": false,
          "source": "public"
        }
      },
      {
        "type": "file",
        "name": "20240626_193250.mp4",
        "path": "재배로그/박/2024_박/20240626/20240626_193250.mp4",
        "extension": "mp4",
        "group": "video",
        "mime_type": "video/mp4",
        "size": 27893088,
        "size_human": "26.6 MB",
        "modified": "2026-07-09T17:49:55+00:00",
        "security": {
          "private": false,
          "source": "public"
        }
      },
      {
        "type": "file",
        "name": "20240626_193308.mp4",
        "path": "재배로그/박/2024_박/20240626/20240626_193308.mp4",
        "extension": "mp4",
        "group": "video",
        "mime_type": "video/mp4",
        "size": 26347048,
        "size_human": "25.1 MB",
        "modified": "2026-07-09T17:49:55+00:00",
        "security": {
          "private": false,
          "source": "public"
        }
      },
      {
        "type": "file",
        "name": "20240626_193328.jpg",
        "path": "재배로그/박/2024_박/20240626/20240626_193328.jpg",
        "extension": "jpg",
        "group": "image",
        "mime_type": "image/jpeg",
        "size": 4834365,
        "size_human": "4.6 MB",
        "modified": "2026-07-09T17:49:55+00:00",
        "security": {
          "private": false,
          "source": "public"
        }
      },
      {
        "type": "file",
        "name": "20240626_193331.jpg",
        "path": "재배로그/박/2024_박/20240626/20240626_193331.jpg",
        "extension": "jpg",
        "group": "image",
        "mime_type": "image/jpeg",
        "size": 4320774,
        "size_human": "4.1 MB",
        "modified": "2026-07-09T17:49:55+00:00",
        "security": {
          "private": false,
          "source": "public"
        }
      },
      {
        "type": "file",
        "name": "20240626_193332.jpg",
        "path": "재배로그/박/2024_박/20240626/20240626_193332.jpg",
        "extension": "jpg",
        "group": "image",
        "mime_type": "image/jpeg",
        "size": 3469096,
        "size_human": "3.3 MB",
        "modified": "2026-07-09T17:49:55+00:00",
        "security": {
          "private": false,
          "source": "public"
        }
      },
      {
        "type": "file",
        "name": "20240626_193454.jpg",
        "path": "재배로그/박/2024_박/20240626/20240626_193454.jpg",
        "extension": "jpg",
        "group": "image",
        "mime_type": "image/jpeg",
        "size": 4953166,
        "size_human": "4.7 MB",
        "modified": "2026-07-09T17:49:55+00:00",
        "security": {
          "private": false,
          "source": "public"
        }
      },
      {
        "type": "file",
        "name": "20240626_193457.jpg",
        "path": "재배로그/박/2024_박/20240626/20240626_193457.jpg",
        "extension": "jpg",
        "group": "image",
        "mime_type": "image/jpeg",
        "size": 2439582,
        "size_human": "2.3 MB",
        "modified": "2026-07-09T17:49:55+00:00",
        "security": {
          "private": false,
          "source": "public"
        }
      },
      {
        "type": "file",
        "name": "20240626_193458.jpg",
        "path": "재배로그/박/2024_박/20240626/20240626_193458.jpg",
        "extension": "jpg",
        "group": "image",
        "mime_type": "image/jpeg",
        "size": 2520848,
        "size_human": "2.4 MB",
        "modified": "2026-07-09T17:49:55+00:00",
        "security": {
          "private": false,
          "source": "public"
        }
      },
      {
        "type": "file",
        "name": "20240626_193502.jpg",
        "path": "재배로그/박/2024_박/20240626/20240626_193502.jpg",
        "extension": "jpg",
        "group": "image",
        "mime_type": "image/jpeg",
        "size": 2169032,
        "size_human": "2.1 MB",
        "modified": "2026-07-09T17:49:55+00:00",
        "security": {
          "private": false,
          "source": "public"
        }
      },
      {
        "type": "file",
        "name": "20240626_193503.jpg",
        "path": "재배로그/박/2024_박/20240626/20240626_193503.jpg",
        "extension": "jpg",
        "group": "image",
        "mime_type": "image/jpeg",
        "size": 1828421,
        "size_human": "1.7 MB",
        "modified": "2026-07-09T17:49:55+00:00",
        "security": {
          "private": false,
          "source": "public"
        }
      },
      {
        "type": "file",
        "name": "20240626_193504.jpg",
        "path": "재배로그/박/2024_박/20240626/20240626_193504.jpg",
        "extension": "jpg",
        "group": "image",
        "mime_type": "image/jpeg",
        "size": 2278286,
        "size_human": "2.2 MB",
        "modified": "2026-07-09T17:49:55+00:00",
        "security": {
          "private": false,
          "source": "public"
        }
      },
      {
        "type": "file",
        "name": "20240626_193505.jpg",
        "path": "재배로그/박/2024_박/20240626/20240626_193505.jpg",
        "extension": "jpg",
        "group": "image",
        "mime_type": "image/jpeg",
        "size": 2103899,
        "size_human": "2.0 MB",
        "modified": "2026-07-09T17:49:55+00:00",
        "security": {
          "private": false,
          "source": "public"
        }
      },
      {
        "type": "file",
        "name": "20240626_193506.jpg",
        "path": "재배로그/박/2024_박/20240626/20240626_193506.jpg",
        "extension": "jpg",
        "group": "image",
        "mime_type": "image/jpeg",
        "size": 2201335,
        "size_human": "2.1 MB",
        "modified": "2026-07-09T17:49:55+00:00",
        "security": {
          "private": false,
          "source": "public"
        }
      },
      {
        "type": "file",
        "name": "20240626_193507.jpg",
        "path": "재배로그/박/2024_박/20240626/20240626_193507.jpg",
        "extension": "jpg",
        "group": "image",
        "mime_type": "image/jpeg",
        "size": 2211502,
        "size_human": "2.1 MB",
        "modified": "2026-07-09T17:49:55+00:00",
        "security": {
          "private": false,
          "source": "public"
        }
      },
      {
        "type": "file",
        "name": "20240626_193512.jpg",
        "path": "재배로그/박/2024_박/20240626/20240626_193512.jpg",
        "extension": "jpg",
        "group": "image",
        "mime_type": "image/jpeg",
        "size": 2807277,
        "size_human": "2.7 MB",
        "modified": "2026-07-09T17:49:55+00:00",
        "security": {
          "private": false,
          "source": "public"
        }
      },
      {
        "type": "file",
        "name": "20240626_193516.mp4",
        "path": "재배로그/박/2024_박/20240626/20240626_193516.mp4",
        "extension": "mp4",
        "group": "video",
        "mime_type": "video/mp4",
        "size": 21673566,
        "size_human": "20.7 MB",
        "modified": "2026-07-09T17:49:55+00:00",
        "security": {
          "private": false,
          "source": "public"
        }
      },
      {
        "type": "file",
        "name": "20240626_193536.jpg",
        "path": "재배로그/박/2024_박/20240626/20240626_193536.jpg",
        "extension": "jpg",
        "group": "image",
        "mime_type": "image/jpeg",
        "size": 3685789,
        "size_human": "3.5 MB",
        "modified": "2026-07-09T17:49:55+00:00",
        "security": {
          "private": false,
          "source": "public"
        }
      },
      {
        "type": "file",
        "name": "20240626_193537.jpg",
        "path": "재배로그/박/2024_박/20240626/20240626_193537.jpg",
        "extension": "jpg",
        "group": "image",
        "mime_type": "image/jpeg",
        "size": 2716650,
        "size_human": "2.6 MB",
        "modified": "2026-07-09T17:49:55+00:00",
        "security": {
          "private": false,
          "source": "public"
        }
      },
      {
        "type": "file",
        "name": "20240626_193540.jpg",
        "path": "재배로그/박/2024_박/20240626/20240626_193540.jpg",
        "extension": "jpg",
        "group": "image",
        "mime_type": "image/jpeg",
        "size": 2726293,
        "size_human": "2.6 MB",
        "modified": "2026-07-09T17:49:55+00:00",
        "security": {
          "private": false,
          "source": "public"
        }
      },
      {
        "type": "file",
        "name": "20240626_193541.jpg",
        "path": "재배로그/박/2024_박/20240626/20240626_193541.jpg",
        "extension": "jpg",
        "group": "image",
        "mime_type": "image/jpeg",
        "size": 2826176,
        "size_human": "2.7 MB",
        "modified": "2026-07-09T17:49:55+00:00",
        "security": {
          "private": false,
          "source": "public"
        }
      },
      {
        "type": "file",
        "name": "20240626_193544.jpg",
        "path": "재배로그/박/2024_박/20240626/20240626_193544.jpg",
        "extension": "jpg",
        "group": "image",
        "mime_type": "image/jpeg",
        "size": 1760718,
        "size_human": "1.7 MB",
        "modified": "2026-07-09T17:49:55+00:00",
        "security": {
          "private": false,
          "source": "public"
        }
      },
      {
        "type": "file",
        "name": "20240626_193546.jpg",
        "path": "재배로그/박/2024_박/20240626/20240626_193546.jpg",
        "extension": "jpg",
        "group": "image",
        "mime_type": "image/jpeg",
        "size": 2735214,
        "size_human": "2.6 MB",
        "modified": "2026-07-09T17:49:55+00:00",
        "security": {
          "private": false,
          "source": "public"
        }
      },
      {
        "type": "file",
        "name": "20240626_193551.mp4",
        "path": "재배로그/박/2024_박/20240626/20240626_193551.mp4",
        "extension": "mp4",
        "group": "video",
        "mime_type": "video/mp4",
        "size": 7169675,
        "size_human": "6.8 MB",
        "modified": "2026-07-09T17:49:55+00:00",
        "security": {
          "private": false,
          "source": "public"
        }
      }
    ],
    "file_count": 32,
    "directory_count": 0,
    "total_size": 228804403,
    "total_size_human": "218.2 MB",
    "security": {
      "private": false,
      "source": "public"
    }
  },
  "files": [
    {
      "type": "file",
      "name": "20240626_193115.jpg",
      "path": "재배로그/박/2024_박/20240626/20240626_193115.jpg",
      "extension": "jpg",
      "group": "image",
      "mime_type": "image/jpeg",
      "size": 2503773,
      "size_human": "2.4 MB",
      "modified": "2026-07-09T17:49:55+00:00",
      "security": {
        "private": false,
        "source": "public"
      }
    },
    {
      "type": "file",
      "name": "20240626_193117.jpg",
      "path": "재배로그/박/2024_박/20240626/20240626_193117.jpg",
      "extension": "jpg",
      "group": "image",
      "mime_type": "image/jpeg",
      "size": 3311368,
      "size_human": "3.2 MB",
      "modified": "2026-07-09T17:49:55+00:00",
      "security": {
        "private": false,
        "source": "public"
      }
    },
    {
      "type": "file",
      "name": "20240626_193124.mp4",
      "path": "재배로그/박/2024_박/20240626/20240626_193124.mp4",
      "extension": "mp4",
      "group": "video",
      "mime_type": "video/mp4",
      "size": 20518873,
      "size_human": "19.6 MB",
      "modified": "2026-07-09T17:49:55+00:00",
      "security": {
        "private": false,
        "source": "public"
      }
    },
    {
      "type": "file",
      "name": "20240626_193143.mp4",
      "path": "재배로그/박/2024_박/20240626/20240626_193143.mp4",
      "extension": "mp4",
      "group": "video",
      "mime_type": "video/mp4",
      "size": 37780691,
      "size_human": "36.0 MB",
      "modified": "2026-07-09T17:49:55+00:00",
      "security": {
        "private": false,
        "source": "public"
      }
    },
    {
      "type": "file",
      "name": "20240626_193210.mp4",
      "path": "재배로그/박/2024_박/20240626/20240626_193210.mp4",
      "extension": "mp4",
      "group": "video",
      "mime_type": "video/mp4",
      "size": 13796023,
      "size_human": "13.2 MB",
      "modified": "2026-07-09T17:49:55+00:00",
      "security": {
        "private": false,
        "source": "public"
      }
    },
    {
      "type": "file",
      "name": "20240626_193242.jpg",
      "path": "재배로그/박/2024_박/20240626/20240626_193242.jpg",
      "extension": "jpg",
      "group": "image",
      "mime_type": "image/jpeg",
      "size": 2613764,
      "size_human": "2.5 MB",
      "modified": "2026-07-09T17:49:55+00:00",
      "security": {
        "private": false,
        "source": "public"
      }
    },
    {
      "type": "file",
      "name": "20240626_193243.jpg",
      "path": "재배로그/박/2024_박/20240626/20240626_193243.jpg",
      "extension": "jpg",
      "group": "image",
      "mime_type": "image/jpeg",
      "size": 3824618,
      "size_human": "3.6 MB",
      "modified": "2026-07-09T17:49:55+00:00",
      "security": {
        "private": false,
        "source": "public"
      }
    },
    {
      "type": "file",
      "name": "20240626_193245.jpg",
      "path": "재배로그/박/2024_박/20240626/20240626_193245.jpg",
      "extension": "jpg",
      "group": "image",
      "mime_type": "image/jpeg",
      "size": 3778942,
      "size_human": "3.6 MB",
      "modified": "2026-07-09T17:49:55+00:00",
      "security": {
        "private": false,
        "source": "public"
      }
    },
    {
      "type": "file",
      "name": "20240626_193246.jpg",
      "path": "재배로그/박/2024_박/20240626/20240626_193246.jpg",
      "extension": "jpg",
      "group": "image",
      "mime_type": "image/jpeg",
      "size": 3004551,
      "size_human": "2.9 MB",
      "modified": "2026-07-09T17:49:55+00:00",
      "security": {
        "private": false,
        "source": "public"
      }
    },
    {
      "type": "file",
      "name": "20240626_193250.mp4",
      "path": "재배로그/박/2024_박/20240626/20240626_193250.mp4",
      "extension": "mp4",
      "group": "video",
      "mime_type": "video/mp4",
      "size": 27893088,
      "size_human": "26.6 MB",
      "modified": "2026-07-09T17:49:55+00:00",
      "security": {
        "private": false,
        "source": "public"
      }
    },
    {
      "type": "file",
      "name": "20240626_193308.mp4",
      "path": "재배로그/박/2024_박/20240626/20240626_193308.mp4",
      "extension": "mp4",
      "group": "video",
      "mime_type": "video/mp4",
      "size": 26347048,
      "size_human": "25.1 MB",
      "modified": "2026-07-09T17:49:55+00:00",
      "security": {
        "private": false,
        "source": "public"
      }
    },
    {
      "type": "file",
      "name": "20240626_193328.jpg",
      "path": "재배로그/박/2024_박/20240626/20240626_193328.jpg",
      "extension": "jpg",
      "group": "image",
      "mime_type": "image/jpeg",
      "size": 4834365,
      "size_human": "4.6 MB",
      "modified": "2026-07-09T17:49:55+00:00",
      "security": {
        "private": false,
        "source": "public"
      }
    },
    {
      "type": "file",
      "name": "20240626_193331.jpg",
      "path": "재배로그/박/2024_박/20240626/20240626_193331.jpg",
      "extension": "jpg",
      "group": "image",
      "mime_type": "image/jpeg",
      "size": 4320774,
      "size_human": "4.1 MB",
      "modified": "2026-07-09T17:49:55+00:00",
      "security": {
        "private": false,
        "source": "public"
      }
    },
    {
      "type": "file",
      "name": "20240626_193332.jpg",
      "path": "재배로그/박/2024_박/20240626/20240626_193332.jpg",
      "extension": "jpg",
      "group": "image",
      "mime_type": "image/jpeg",
      "size": 3469096,
      "size_human": "3.3 MB",
      "modified": "2026-07-09T17:49:55+00:00",
      "security": {
        "private": false,
        "source": "public"
      }
    },
    {
      "type": "file",
      "name": "20240626_193454.jpg",
      "path": "재배로그/박/2024_박/20240626/20240626_193454.jpg",
      "extension": "jpg",
      "group": "image",
      "mime_type": "image/jpeg",
      "size": 4953166,
      "size_human": "4.7 MB",
      "modified": "2026-07-09T17:49:55+00:00",
      "security": {
        "private": false,
        "source": "public"
      }
    },
    {
      "type": "file",
      "name": "20240626_193457.jpg",
      "path": "재배로그/박/2024_박/20240626/20240626_193457.jpg",
      "extension": "jpg",
      "group": "image",
      "mime_type": "image/jpeg",
      "size": 2439582,
      "size_human": "2.3 MB",
      "modified": "2026-07-09T17:49:55+00:00",
      "security": {
        "private": false,
        "source": "public"
      }
    },
    {
      "type": "file",
      "name": "20240626_193458.jpg",
      "path": "재배로그/박/2024_박/20240626/20240626_193458.jpg",
      "extension": "jpg",
      "group": "image",
      "mime_type": "image/jpeg",
      "size": 2520848,
      "size_human": "2.4 MB",
      "modified": "2026-07-09T17:49:55+00:00",
      "security": {
        "private": false,
        "source": "public"
      }
    },
    {
      "type": "file",
      "name": "20240626_193502.jpg",
      "path": "재배로그/박/2024_박/20240626/20240626_193502.jpg",
      "extension": "jpg",
      "group": "image",
      "mime_type": "image/jpeg",
      "size": 2169032,
      "size_human": "2.1 MB",
      "modified": "2026-07-09T17:49:55+00:00",
      "security": {
        "private": false,
        "source": "public"
      }
    },
    {
      "type": "file",
      "name": "20240626_193503.jpg",
      "path": "재배로그/박/2024_박/20240626/20240626_193503.jpg",
      "extension": "jpg",
      "group": "image",
      "mime_type": "image/jpeg",
      "size": 1828421,
      "size_human": "1.7 MB",
      "modified": "2026-07-09T17:49:55+00:00",
      "security": {
        "private": false,
        "source": "public"
      }
    },
    {
      "type": "file",
      "name": "20240626_193504.jpg",
      "path": "재배로그/박/2024_박/20240626/20240626_193504.jpg",
      "extension": "jpg",
      "group": "image",
      "mime_type": "image/jpeg",
      "size": 2278286,
      "size_human": "2.2 MB",
      "modified": "2026-07-09T17:49:55+00:00",
      "security": {
        "private": false,
        "source": "public"
      }
    },
    {
      "type": "file",
      "name": "20240626_193505.jpg",
      "path": "재배로그/박/2024_박/20240626/20240626_193505.jpg",
      "extension": "jpg",
      "group": "image",
      "mime_type": "image/jpeg",
      "size": 2103899,
      "size_human": "2.0 MB",
      "modified": "2026-07-09T17:49:55+00:00",
      "security": {
        "private": false,
        "source": "public"
      }
    },
    {
      "type": "file",
      "name": "20240626_193506.jpg",
      "path": "재배로그/박/2024_박/20240626/20240626_193506.jpg",
      "extension": "jpg",
      "group": "image",
      "mime_type": "image/jpeg",
      "size": 2201335,
      "size_human": "2.1 MB",
      "modified": "2026-07-09T17:49:55+00:00",
      "security": {
        "private": false,
        "source": "public"
      }
    },
    {
      "type": "file",
      "name": "20240626_193507.jpg",
      "path": "재배로그/박/2024_박/20240626/20240626_193507.jpg",
      "extension": "jpg",
      "group": "image",
      "mime_type": "image/jpeg",
      "size": 2211502,
      "size_human": "2.1 MB",
      "modified": "2026-07-09T17:49:55+00:00",
      "security": {
        "private": false,
        "source": "public"
      }
    },
    {
      "type": "file",
      "name": "20240626_193512.jpg",
      "path": "재배로그/박/2024_박/20240626/20240626_193512.jpg",
      "extension": "jpg",
      "group": "image",
      "mime_type": "image/jpeg",
      "size": 2807277,
      "size_human": "2.7 MB",
      "modified": "2026-07-09T17:49:55+00:00",
      "security": {
        "private": false,
        "source": "public"
      }
    },
    {
      "type": "file",
      "name": "20240626_193516.mp4",
      "path": "재배로그/박/2024_박/20240626/20240626_193516.mp4",
      "extension": "mp4",
      "group": "video",
      "mime_type": "video/mp4",
      "size": 21673566,
      "size_human": "20.7 MB",
      "modified": "2026-07-09T17:49:55+00:00",
      "security": {
        "private": false,
        "source": "public"
      }
    },
    {
      "type": "file",
      "name": "20240626_193536.jpg",
      "path": "재배로그/박/2024_박/20240626/20240626_193536.jpg",
      "extension": "jpg",
      "group": "image",
      "mime_type": "image/jpeg",
      "size": 3685789,
      "size_human": "3.5 MB",
      "modified": "2026-07-09T17:49:55+00:00",
      "security": {
        "private": false,
        "source": "public"
      }
    },
    {
      "type": "file",
      "name": "20240626_193537.jpg",
      "path": "재배로그/박/2024_박/20240626/20240626_193537.jpg",
      "extension": "jpg",
      "group": "image",
      "mime_type": "image/jpeg",
      "size": 2716650,
      "size_human": "2.6 MB",
      "modified": "2026-07-09T17:49:55+00:00",
      "security": {
        "private": false,
        "source": "public"
      }
    },
    {
      "type": "file",
      "name": "20240626_193540.jpg",
      "path": "재배로그/박/2024_박/20240626/20240626_193540.jpg",
      "extension": "jpg",
      "group": "image",
      "mime_type": "image/jpeg",
      "size": 2726293,
      "size_human": "2.6 MB",
      "modified": "2026-07-09T17:49:55+00:00",
      "security": {
        "private": false,
        "source": "public"
      }
    },
    {
      "type": "file",
      "name": "20240626_193541.jpg",
      "path": "재배로그/박/2024_박/20240626/20240626_193541.jpg",
      "extension": "jpg",
      "group": "image",
      "mime_type": "image/jpeg",
      "size": 2826176,
      "size_human": "2.7 MB",
      "modified": "2026-07-09T17:49:55+00:00",
      "security": {
        "private": false,
        "source": "public"
      }
    },
    {
      "type": "file",
      "name": "20240626_193544.jpg",
      "path": "재배로그/박/2024_박/20240626/20240626_193544.jpg",
      "extension": "jpg",
      "group": "image",
      "mime_type": "image/jpeg",
      "size": 1760718,
      "size_human": "1.7 MB",
      "modified": "2026-07-09T17:49:55+00:00",
      "security": {
        "private": false,
        "source": "public"
      }
    },
    {
      "type": "file",
      "name": "20240626_193546.jpg",
      "path": "재배로그/박/2024_박/20240626/20240626_193546.jpg",
      "extension": "jpg",
      "group": "image",
      "mime_type": "image/jpeg",
      "size": 2735214,
      "size_human": "2.6 MB",
      "modified": "2026-07-09T17:49:55+00:00",
      "security": {
        "private": false,
        "source": "public"
      }
    },
    {
      "type": "file",
      "name": "20240626_193551.mp4",
      "path": "재배로그/박/2024_박/20240626/20240626_193551.mp4",
      "extension": "mp4",
      "group": "video",
      "mime_type": "video/mp4",
      "size": 7169675,
      "size_human": "6.8 MB",
      "modified": "2026-07-09T17:49:55+00:00",
      "security": {
        "private": false,
        "source": "public"
      }
    }
  ],
  "child_indexes": [],
  "errors": []
}